Metadata-Version: 2.4
Name: SharedPubSub
Version: 1.0.0
Summary: Shared memory Publisher and Subscriber library
Home-page: https://github.com/SimonNGN/SharedPubSub
Author: Simon Nguyen
License-Expression: MIT
Project-URL: Homepage, https://github.com/SimonNGN/SharedPubSub
Project-URL: Issues, https://github.com/SimonNGN/SharedPubSub/issues
Classifier: Programming Language :: Python :: 3
Classifier: Operating System :: POSIX :: Linux
Requires-Python: >=3.10
License-File: LICENSE
Dynamic: home-page
Dynamic: license-file
